covatls/__init__.py
covatls/AES/AESCipher.py
covatls/AES/__init__.py
covatls/client/__init__.py
covatls/client/cova_client_request.py
covatls/client/test_client.py
covatls/server/__init__.py
covatls/server/cova_server.py
covatls/server/handshake.py
covatls/server/test_server.py
covatls-0.1.3.dist-info/LICENSE
covatls-0.1.3.dist-info/METADATA
covatls-0.1.3.dist-info/WHEEL
covatls-0.1.3.dist-info/top_level.txt
covatls-0.1.3.dist-info/RECORD
