Metadata-Version: 2.1
Name: covatls
Version: 0.1.3
Summary: TLS layer like https protocol
Home-page: https://github.com/covalent-hq/cova-core/tree/covatls/core/covatls
Author: Covalent AI
Author-email: contact@covalent.ai
License: UNKNOWN
Platform: UNKNOWN
Classifier: Programming Language :: Python :: 2.7
Classifier: License :: OSI Approved :: MIT License
Classifier: Operating System :: OS Independent
Requires-Dist: pycrypto
